preserve/__init__.py
preserve/cli.py
preserve/connector.py
preserve/connectors/__init__.py
preserve/connectors/memory.py
preserve/connectors/mongo.py
preserve/connectors/shelf.py
preserve/connectors/sqlite.py
preserve/preserve.py
preserve/utils.py
preserve-1.2.1.dist-info/LICENSE
preserve-1.2.1.dist-info/METADATA
preserve-1.2.1.dist-info/WHEEL
preserve-1.2.1.dist-info/entry_points.txt
preserve-1.2.1.dist-info/RECORD
