Metadata-Version: 2.3
Name: preserve
Version: 1.2.1
Summary: A simple key/value store with multiple backends.
License: MIT
Author: Grégoire Burel
Author-email: evhart@users.noreply.github.com
Requires-Python: >=3.9,<4.0
Classifier: Development Status :: 3 - Alpha
Classifier: Intended Audience :: Developers
Classifier: Intended Audience :: System Administrators
Classifier: License :: OSI Approved :: MIT License
Classifier: Operating System :: OS Independent
Classifier: Programming Language :: Python
Classifier: Programming Language :: Python :: 3
Classifier: Programming Language :: Python :: 3.9
Classifier: Programming Language :: Python :: 3.10
Classifier: Programming Language :: Python :: 3.11
Classifier: Programming Language :: Python :: 3.12
Classifier: Programming Language :: Python :: 3.13
Classifier: Programming Language :: Python :: Implementation :: PyPy
Classifier: Topic :: Database
Classifier: Topic :: Database :: Database Engines/Servers
Classifier: Topic :: Utilities
Provides-Extra: mongodb
Requires-Dist: halo (>=0.0.30,<0.0.31)
Requires-Dist: pydantic (>=2.0.0,<3.0.0)
Requires-Dist: pymongo (>=4.5.0,<5.0.0) ; extra == "mongodb"
Requires-Dist: setuptools (>=75.8.0,<76.0.0)
Requires-Dist: tabulate (>=0.8.7,<0.9.0)
Requires-Dist: toml (>=0.10.1,<0.11.0)
Requires-Dist: typer (>=0.4.0,<1.0.0)
Requires-Dist: usingversion (>=0.1.2,<0.2.0)
Project-URL: Homepage, https://github.com/evhart/preserve/
Project-URL: Repository, https://github.com/evhart/preserve/
